{
  "total_samples": 3,
  "zero_rasterized_minutiae_samples": 0,
  "by_view_role": {
    "front": {
      "sample_count": 1,
      "zero_rasterized_minutiae_samples": 0,
      "minutiae_count_sum": 144,
      "rasterized_minutiae_count_sum": 141,
      "rasterized_minutiae_count_min": 141,
      "rasterized_minutiae_count_max": 141,
      "used_reconstruction_backed_final_labels": 1,
      "used_direct_fallback": 0,
      "mean_minutiae_count": 144.0,
      "mean_rasterized_minutiae_count": 141.0,
      "zero_rasterized_minutiae_fraction": 0.0
    },
    "left": {
      "sample_count": 1,
      "zero_rasterized_minutiae_samples": 0,
      "minutiae_count_sum": 71,
      "rasterized_minutiae_count_sum": 71,
      "rasterized_minutiae_count_min": 71,
      "rasterized_minutiae_count_max": 71,
      "used_reconstruction_backed_final_labels": 0,
      "used_direct_fallback": 1,
      "mean_minutiae_count": 71.0,
      "mean_rasterized_minutiae_count": 71.0,
      "zero_rasterized_minutiae_fraction": 0.0
    },
    "right": {
      "sample_count": 1,
      "zero_rasterized_minutiae_samples": 0,
      "minutiae_count_sum": 62,
      "rasterized_minutiae_count_sum": 62,
      "rasterized_minutiae_count_min": 62,
      "rasterized_minutiae_count_max": 62,
      "used_reconstruction_backed_final_labels": 0,
      "used_direct_fallback": 1,
      "mean_minutiae_count": 62.0,
      "mean_rasterized_minutiae_count": 62.0,
      "zero_rasterized_minutiae_fraction": 0.0
    }
  },
  "by_raw_view_index": {
    "0": {
      "sample_count": 1,
      "zero_rasterized_minutiae_samples": 0,
      "minutiae_count_sum": 144,
      "rasterized_minutiae_count_sum": 141,
      "rasterized_minutiae_count_min": 141,
      "rasterized_minutiae_count_max": 141,
      "used_reconstruction_backed_final_labels": 1,
      "used_direct_fallback": 0,
      "mean_minutiae_count": 144.0,
      "mean_rasterized_minutiae_count": 141.0,
      "zero_rasterized_minutiae_fraction": 0.0
    },
    "1": {
      "sample_count": 1,
      "zero_rasterized_minutiae_samples": 0,
      "minutiae_count_sum": 71,
      "rasterized_minutiae_count_sum": 71,
      "rasterized_minutiae_count_min": 71,
      "rasterized_minutiae_count_max": 71,
      "used_reconstruction_backed_final_labels": 0,
      "used_direct_fallback": 1,
      "mean_minutiae_count": 71.0,
      "mean_rasterized_minutiae_count": 71.0,
      "zero_rasterized_minutiae_fraction": 0.0
    },
    "2": {
      "sample_count": 1,
      "zero_rasterized_minutiae_samples": 0,
      "minutiae_count_sum": 62,
      "rasterized_minutiae_count_sum": 62,
      "rasterized_minutiae_count_min": 62,
      "rasterized_minutiae_count_max": 62,
      "used_reconstruction_backed_final_labels": 0,
      "used_direct_fallback": 1,
      "mean_minutiae_count": 62.0,
      "mean_rasterized_minutiae_count": 62.0,
      "zero_rasterized_minutiae_fraction": 0.0
    }
  },
  "by_mode": {
    "reconstruction_backed": {
      "sample_count": 1,
      "zero_rasterized_minutiae_samples": 0,
      "minutiae_count_sum": 144,
      "rasterized_minutiae_count_sum": 141,
      "rasterized_minutiae_count_min": 141,
      "rasterized_minutiae_count_max": 141,
      "used_reconstruction_backed_final_labels": 1,
      "used_direct_fallback": 0,
      "mean_minutiae_count": 144.0,
      "mean_rasterized_minutiae_count": 141.0,
      "zero_rasterized_minutiae_fraction": 0.0
    },
    "direct_fallback_after_empty_reprojection": {
      "sample_count": 2,
      "zero_rasterized_minutiae_samples": 0,
      "minutiae_count_sum": 133,
      "rasterized_minutiae_count_sum": 133,
      "rasterized_minutiae_count_min": 62,
      "rasterized_minutiae_count_max": 71,
      "used_reconstruction_backed_final_labels": 0,
      "used_direct_fallback": 2,
      "mean_minutiae_count": 66.5,
      "mean_rasterized_minutiae_count": 66.5,
      "zero_rasterized_minutiae_fraction": 0.0
    }
  },
  "zero_rasterized_minutiae_fraction": 0.0
}