[
  {
    "x": 245.0,
    "y": 214.0,
    "theta": 0.12281573563814163,
    "score": 0.6649991869926453,
    "type": "E",
    "source": "pyfing"
  },
  {
    "x": 254.0,
    "y": 233.0,
    "theta": 5.984756205474035,
    "score": 0.8505274653434753,
    "type": "E",
    "source": "pyfing"
  },
  {
    "x": 242.0,
    "y": 249.0,
    "theta": 6.061589394007818,
    "score": 0.7736905217170715,
    "type": "B",
    "source": "pyfing"
  },
  {
    "x": 277.0,
    "y": 259.0,
    "theta": 5.519527200852529,
    "score": 0.9106539487838745,
    "type": "E",
    "source": "pyfing"
  },
  {
    "x": 328.0,
    "y": 273.0,
    "theta": 5.36704790989031,
    "score": 0.8906303644180298,
    "type": "B",
    "source": "pyfing"
  },
  {
    "x": 301.0,
    "y": 318.0,
    "theta": 5.081459347401754,
    "score": 0.8455604910850525,
    "type": "B",
    "source": "pyfing"
  },
  {
    "x": 217.0,
    "y": 326.0,
    "theta": 4.460729900990621,
    "score": 0.7032905220985413,
    "type": "B",
    "source": "pyfing"
  },
  {
    "x": 268.0,
    "y": 329.0,
    "theta": 4.9942291418658655,
    "score": 0.7664207816123962,
    "type": "B",
    "source": "pyfing"
  },
  {
    "x": 249.0,
    "y": 344.0,
    "theta": 4.631361667309896,
    "score": 0.7994201183319092,
    "type": "B",
    "source": "pyfing"
  },
  {
    "x": 238.0,
    "y": 354.0,
    "theta": 4.609387580548422,
    "score": 0.60865718126297,
    "type": "B",
    "source": "pyfing"
  },
  {
    "x": 306.0,
    "y": 356.0,
    "theta": 5.064059440289633,
    "score": 0.9287196397781372,
    "type": "E",
    "source": "pyfing"
  },
  {
    "x": 228.0,
    "y": 358.0,
    "theta": 4.365142289792196,
    "score": 0.8181252479553223,
    "type": "B",
    "source": "pyfing"
  },
  {
    "x": 254.0,
    "y": 361.0,
    "theta": 1.4549343585968018,
    "score": 0.6824471354484558,
    "type": "B",
    "source": "pyfing"
  },
  {
    "x": 274.0,
    "y": 369.0,
    "theta": 4.649977986012594,
    "score": 0.6533718705177307,
    "type": "B",
    "source": "pyfing"
  },
  {
    "x": 217.0,
    "y": 381.0,
    "theta": 4.1324361006366175,
    "score": 0.8956551551818848,
    "type": "B",
    "source": "pyfing"
  },
  {
    "x": 270.0,
    "y": 388.0,
    "theta": 1.49753737449646,
    "score": 0.913531482219696,
    "type": "B",
    "source": "pyfing"
  },
  {
    "x": 277.0,
    "y": 406.0,
    "theta": 4.363454763089315,
    "score": 0.7869587540626526,
    "type": "E",
    "source": "pyfing"
  },
  {
    "x": 286.0,
    "y": 412.0,
    "theta": 4.647144142781393,
    "score": 0.6004132628440857,
    "type": "E",
    "source": "pyfing"
  },
  {
    "x": 305.0,
    "y": 416.0,
    "theta": 5.0150514284717005,
    "score": 0.8878483176231384,
    "type": "B",
    "source": "pyfing"
  },
  {
    "x": 260.0,
    "y": 425.0,
    "theta": 1.0332359075546265,
    "score": 0.7807000279426575,
    "type": "B",
    "source": "pyfing"
  },
  {
    "x": 235.0,
    "y": 437.0,
    "theta": 0.7363138794898987,
    "score": 0.8995760679244995,
    "type": "B",
    "source": "pyfing"
  }
]